LICENSE
README.md
setup.py
korus/__init__.py
korus/db.py
korus/selection.py
korus/tax.py
korus/tree.py
korus/util.py
korus.egg-info/PKG-INFO
korus.egg-info/SOURCES.txt
korus.egg-info/dependency_links.txt
korus.egg-info/entry_points.txt
korus.egg-info/not-zip-safe
korus.egg-info/requires.txt
korus.egg-info/top_level.txt
korus/app/__init__.py
korus/app/submit.py
korus/app/app_util/__init__.py
korus/app/app_util/add.py
korus/app/app_util/ui.py
korus/app/app_util/view.py
korus/db_util/__init__.py
korus/db_util/label.py
korus/db_util/table.py
korus/tests/__init__.py
korus/tests/cleanup.py
korus/tests/conftest.py
korus/tests/test_db.py
korus/tests/test_selection.py
korus/tests/test_tax.py
korus/tests/test_tree.py
korus/tests/test_tutorials.py
korus/tests/test_util.py
korus/tests/app/__init__.py
korus/tests/app/app_util/__init__.py
korus/tests/app/app_util/test_add.py
korus/tests/db_util/__init__.py
korus/tests/db_util/test_label.py