Metadata-Version: 2.1
Name: korus
Version: 0.0.10
Summary: Python package for managing acoustic metadata and annotations
Home-page: https://github.com/meridian-analytics/korus
Author: Oliver Kirsebom
Author-email: oliver.kirsebom@gmail.com
License: UNKNOWN
Platform: UNKNOWN
License-File: LICENSE
